dune_analytics/__init__.py
dune_analytics_fix-0.0.8.dist-info/LICENSE
dune_analytics_fix-0.0.8.dist-info/METADATA
dune_analytics_fix-0.0.8.dist-info/WHEEL
dune_analytics_fix-0.0.8.dist-info/top_level.txt
dune_analytics_fix-0.0.8.dist-info/RECORD
