Metadata-Version: 2.1
Name: dune-analytics-fix
Version: 0.0.8
Summary: An interface for querying Dune Analytics
Home-page: https://github.com/git-alice/dune-analytics
Author: Justin Martin
Author-email: justin@jmart.me
License: UNKNOWN
Project-URL: Bug Tracker, https://github.com/git-alice/dune-analytics/issues
Platform: UNKNOWN
Classifier: Programming Language :: Python :: 3
Classifier: License :: OSI Approved :: MIT License
Classifier: Operating System :: OS Independent
Requires-Python: >=3.6
Requires-Dist: gql[aiohttp] (==2.0.0)
